{"schema_version":"1.0","category_zh":"科研管理、专利与诚信","part":3,"count":8,"capabilities":[{"id":"S0315","slug":"research-integrity-checker","name_zh":"科研诚信检查","name_en":"Research Integrity Checker","category_zh":"科研管理、专利与诚信","description_zh":"检查数据、图像、统计和引用风险","workflow":"research-integrity","triggers":["科研诚信检查","research-integrity-checker"],"inputs":["manuscript_or_dataset","audit_scope","provenance"],"outputs":["integrity_findings","evidence_log","severity","recommended_actions"],"recommended_tools":["ARS","ARIS","项目管理与专利工具"],"risk_level":"high","human_approval_required":true,"tsao_sci_computation_handoff":"none","references":["references/integrity/integrity-gates.md","references/integrity/claim-evidence-policy.md"]},{"id":"S0316","slug":"image-manipulation-detector","name_zh":"科研图像异常","name_en":"Image Manipulation Detector","category_zh":"科研管理、专利与诚信","description_zh":"检查重复、拼接、缩放和处理痕迹","workflow":"research-integrity","triggers":["科研图像异常","image-manipulation-detector"],"inputs":["manuscript_or_dataset","audit_scope","provenance"],"outputs":["integrity_findings","evidence_log","severity","recommended_actions"],"recommended_tools":["ARS","ARIS","项目管理与专利工具"],"risk_level":"medium","human_approval_required":true,"tsao_sci_computation_handoff":"none","references":["references/integrity/integrity-gates.md","references/integrity/claim-evidence-policy.md"]},{"id":"S0317","slug":"p-hacking-checker","name_zh":"统计操纵检查","name_en":"P Hacking Checker","category_zh":"科研管理、专利与诚信","description_zh":"识别多重检验、选择性报告和事后假设","workflow":"research-integrity","triggers":["统计操纵检查","p-hacking-checker"],"inputs":["manuscript_or_dataset","audit_scope","provenance"],"outputs":["integrity_findings","evidence_log","severity","recommended_actions"],"recommended_tools":["ARS","ARIS","项目管理与专利工具"],"risk_level":"medium","human_approval_required":true,"tsao_sci_computation_handoff":"none","references":["references/integrity/integrity-gates.md","references/integrity/claim-evidence-policy.md"]},{"id":"S0318","slug":"data-fabrication-anomaly","name_zh":"数据造假异常","name_en":"Data Fabrication Anomaly","category_zh":"科研管理、专利与诚信","description_zh":"识别不自然分布、重复模式和数字异常","workflow":"research-integrity","triggers":["数据造假异常","data-fabrication-anomaly"],"inputs":["manuscript_or_dataset","audit_scope","provenance"],"outputs":["integrity_findings","evidence_log","severity","recommended_actions"],"recommended_tools":["ARS","ARIS","项目管理与专利工具"],"risk_level":"high","human_approval_required":true,"tsao_sci_computation_handoff":"none","references":["references/integrity/integrity-gates.md","references/integrity/claim-evidence-policy.md"]},{"id":"S0319","slug":"citation-misrepresentation","name_zh":"引用误用检查","name_en":"Citation Misrepresentation","category_zh":"科研管理、专利与诚信","description_zh":"检查文献是否真正支持所述结论","workflow":"research-integrity","triggers":["引用误用检查","citation-misrepresentation"],"inputs":["manuscript_or_dataset","audit_scope","provenance"],"outputs":["integrity_findings","evidence_log","severity","recommended_actions"],"recommended_tools":["ARS","ARIS","项目管理与专利工具"],"risk_level":"medium","human_approval_required":true,"tsao_sci_computation_handoff":"none","references":["references/integrity/integrity-gates.md","references/integrity/claim-evidence-policy.md"]},{"id":"S0320","slug":"evidence-level-labeler","name_zh":"证据等级","name_en":"Evidence Level Labeler","category_zh":"科研管理、专利与诚信","description_zh":"给科研结论标注证据来源和等级","workflow":"research-integrity","triggers":["证据等级","evidence-level-labeler"],"inputs":["manuscript_or_dataset","audit_scope","provenance"],"outputs":["integrity_findings","evidence_log","severity","recommended_actions"],"recommended_tools":["ARS","ARIS","项目管理与专利工具"],"risk_level":"medium","human_approval_required":true,"tsao_sci_computation_handoff":"none","references":["references/integrity/integrity-gates.md","references/integrity/claim-evidence-policy.md"]},{"id":"S0321","slug":"hallucination-guard","name_zh":"科研幻觉防护","name_en":"Hallucination Guard","category_zh":"科研管理、专利与诚信","description_zh":"禁止把未运行计算、未观察实验写成事实","workflow":"research-integrity","triggers":["科研幻觉防护","hallucination-guard"],"inputs":["manuscript_or_dataset","audit_scope","provenance"],"outputs":["integrity_findings","evidence_log","severity","recommended_actions"],"recommended_tools":["ARS","ARIS","项目管理与专利工具"],"risk_level":"medium","human_approval_required":true,"tsao_sci_computation_handoff":"none","references":["references/integrity/integrity-gates.md","references/integrity/claim-evidence-policy.md"]},{"id":"S0322","slug":"model-governance","name_zh":"科研模型治理","name_en":"Model Governance","category_zh":"科研管理、专利与诚信","description_zh":"管理模型版本、适用域、审批和责任","workflow":"research-integrity","triggers":["科研模型治理","model-governance"],"inputs":["manuscript_or_dataset","audit_scope","provenance"],"outputs":["integrity_findings","evidence_log","severity","recommended_actions"],"recommended_tools":["ARS","ARIS","项目管理与专利工具"],"risk_level":"medium","human_approval_required":true,"tsao_sci_computation_handoff":"none","references":["references/integrity/integrity-gates.md","references/integrity/claim-evidence-policy.md"]}]}
