{"schema_version":"1.0","category_zh":"文献与知识工程","part":2,"count":8,"capabilities":[{"id":"S0027","slug":"contradiction-finder","name_zh":"文献矛盾发现","name_en":"Contradiction Finder","category_zh":"文献与知识工程","description_zh":"定位不同研究之间的结论冲突及条件差异","workflow":"deep-research","triggers":["文献矛盾发现","contradiction-finder"],"inputs":["research_question","scope","date_range","source_constraints"],"outputs":["search_strategy","evidence_map","source_log","research_gap_report"],"recommended_tools":["PaperQA","ARS","Deep Research"],"risk_level":"low","human_approval_required":false,"tsao_sci_computation_handoff":"none","references":["references/literature/search-and-evidence.md","references/integrity/claim-evidence-policy.md"]},{"id":"S0028","slug":"method-extractor","name_zh":"方法提取","name_en":"Method Extractor","category_zh":"文献与知识工程","description_zh":"提取可复现实验或计算流程","workflow":"deep-research","triggers":["方法提取","method-extractor"],"inputs":["research_question","scope","date_range","source_constraints"],"outputs":["search_strategy","evidence_map","source_log","research_gap_report"],"recommended_tools":["PaperQA","ARS","Deep Research"],"risk_level":"low","human_approval_required":false,"tsao_sci_computation_handoff":"none","references":["references/literature/search-and-evidence.md","references/integrity/claim-evidence-policy.md"]},{"id":"S0029","slug":"parameter-extractor","name_zh":"参数提取","name_en":"Parameter Extractor","category_zh":"文献与知识工程","description_zh":"提取温度、压力、时间、浓度、模型与软件参数","workflow":"deep-research","triggers":["参数提取","parameter-extractor"],"inputs":["research_question","scope","date_range","source_constraints"],"outputs":["search_strategy","evidence_map","source_log","research_gap_report"],"recommended_tools":["PaperQA","ARS","Deep Research"],"risk_level":"low","human_approval_required":false,"tsao_sci_computation_handoff":"none","references":["references/literature/search-and-evidence.md","references/integrity/claim-evidence-policy.md"]},{"id":"S0030","slug":"claim-evidence-linker","name_zh":"结论证据关联","name_en":"Claim Evidence Linker","category_zh":"文献与知识工程","description_zh":"将论断关联到原文、图表和数据位置","workflow":"systematic-review","triggers":["结论证据关联","claim-evidence-linker"],"inputs":["protocol","eligibility_criteria","databases","screening_records"],"outputs":["prisma_log","included_studies","quality_assessment","evidence_synthesis"],"recommended_tools":["PaperQA","ARS","Deep Research"],"risk_level":"low","human_approval_required":false,"tsao_sci_computation_handoff":"none","references":["references/literature/systematic-review.md","references/statistics/method-selection.md"]},{"id":"S0031","slug":"reference-integrity-checker","name_zh":"参考文献完整性","name_en":"Reference Integrity Checker","category_zh":"文献与知识工程","description_zh":"检查伪造、错配、缺失和无支撑引用","workflow":"systematic-review","triggers":["参考文献完整性","reference-integrity-checker"],"inputs":["protocol","eligibility_criteria","databases","screening_records"],"outputs":["prisma_log","included_studies","quality_assessment","evidence_synthesis"],"recommended_tools":["PaperQA","ARS","Deep Research"],"risk_level":"high","human_approval_required":true,"tsao_sci_computation_handoff":"none","references":["references/literature/systematic-review.md","references/statistics/method-selection.md"]},{"id":"S0032","slug":"literature-deduplicator","name_zh":"文献去重","name_en":"Literature Deduplicator","category_zh":"文献与知识工程","description_zh":"处理预印本、正式论文和重复数据库记录","workflow":"systematic-review","triggers":["文献去重","literature-deduplicator"],"inputs":["protocol","eligibility_criteria","databases","screening_records"],"outputs":["prisma_log","included_studies","quality_assessment","evidence_synthesis"],"recommended_tools":["PaperQA","ARS","Deep Research"],"risk_level":"low","human_approval_required":false,"tsao_sci_computation_handoff":"none","references":["references/literature/systematic-review.md","references/statistics/method-selection.md"]},{"id":"S0033","slug":"research-knowledge-graph","name_zh":"科研知识图谱","name_en":"Research Knowledge Graph","category_zh":"文献与知识工程","description_zh":"建立作者—材料—方法—性能—证据关系","workflow":"deep-research","triggers":["科研知识图谱","research-knowledge-graph"],"inputs":["research_question","scope","date_range","source_constraints"],"outputs":["search_strategy","evidence_map","source_log","research_gap_report"],"recommended_tools":["PaperQA","ARS","Deep Research"],"risk_level":"low","human_approval_required":false,"tsao_sci_computation_handoff":"none","references":["references/literature/search-and-evidence.md","references/integrity/claim-evidence-policy.md"]},{"id":"S0034","slug":"semantic-indexer","name_zh":"科学语义索引","name_en":"Semantic Indexer","category_zh":"文献与知识工程","description_zh":"建立向量、关键词和结构化混合索引","workflow":"deep-research","triggers":["科学语义索引","semantic-indexer"],"inputs":["research_question","scope","date_range","source_constraints"],"outputs":["search_strategy","evidence_map","source_log","research_gap_report"],"recommended_tools":["PaperQA","ARS","Deep Research"],"risk_level":"low","human_approval_required":false,"tsao_sci_computation_handoff":"none","references":["references/literature/search-and-evidence.md","references/integrity/claim-evidence-policy.md"]}]}
